setup.py
wechat/__init__.py
wechat/crypt.py
wechat/enterprise.py
wechat/models.py
wechat/official.py
wechat.egg-info/PKG-INFO
wechat.egg-info/SOURCES.txt
wechat.egg-info/dependency_links.txt
wechat.egg-info/requires.txt
wechat.egg-info/top_level.txt