Metadata-Version: 1.0
Name: wechat
Version: 0.4.12
Summary: Wechat Python SDK
Home-page: https://github.com/jeffkit/wechat
Author: jeff kit
Author-email: bbmyth@gmail.com
License: UNKNOWN
Platform: UNKNOWN
